readcsvturbo/__init__.py
readcsvturbo/readcsvturbo.py
readcsvturbo/speedtest.py
readcsvturbo/test.py
readcsvturbo-0.0.6.dist-info/METADATA
readcsvturbo-0.0.6.dist-info/WHEEL
readcsvturbo-0.0.6.dist-info/top_level.txt
readcsvturbo-0.0.6.dist-info/RECORD
