Metadata-Version: 2.1
Name: readcsvturbo
Version: 0.0.6
Summary: Improved method for reading the first/last/specific line from csv into a DataFrame
Home-page: https://github.com/donjor/read-csv-turbo
Author: Donjor
Author-email: donjordev@gmail.com
License: UNKNOWN
Keywords: python,pandas,readcsv,readfirstlinecsv,readlastlinecsv,readspecificlinecsv
Platform: UNKNOWN
Classifier: Development Status :: 3 - Alpha
Classifier: Programming Language :: Python :: 3
Classifier: Operating System :: MacOS :: MacOS X
Classifier: Operating System :: POSIX :: Linux
Classifier: Operating System :: Microsoft :: Windows
Requires-Dist: pandas
